symderive/__init__.py
symderive/agents/AGENTS.yaml
symderive/agents/__init__.py
symderive/agents/atiyah.agent.md
symderive/agents/beavis.agent.md
symderive/agents/billpress.agent.md
symderive/agents/butthead.agent.md
symderive/agents/ed.agent.md
symderive/agents/edwardtufte.agent.md
symderive/agents/grothendieck.agent.md
symderive/agents/jimsimons.agent.md
symderive/agents/steve.agent.md
symderive/algebra/__init__.py
symderive/algebra/linear.py
symderive/algebra/simplify.py
symderive/algebra/solve.py
symderive/calculus/__init__.py
symderive/calculus/differentiation.py
symderive/calculus/greens.py
symderive/calculus/integration.py
symderive/calculus/limits.py
symderive/calculus/series.py
symderive/calculus/transforms.py
symderive/calculus/variational.py
symderive/compact/__init__.py
symderive/compact/constraints.py
symderive/compact/io.py
symderive/compact/models.py
symderive/compact/regression.py
symderive/core/__init__.py
symderive/core/constants.py
symderive/core/math_api.py
symderive/core/numbers.py
symderive/core/symbols.py
symderive/data/__init__.py
symderive/data/io.py
symderive/data/lists.py
symderive/diffgeo/__init__.py
symderive/diffgeo/einsum.py
symderive/diffgeo/indices.py
symderive/diffgeo/metrics.py
symderive/diffgeo/symmetry.py
symderive/diffgeo/transforms.py
symderive/discretization/__init__.py
symderive/discretization/stencils.py
symderive/functions/__init__.py
symderive/functions/complex.py
symderive/functions/exponential.py
symderive/functions/number.py
symderive/functions/special.py
symderive/functions/trig.py
symderive/functions/utils.py
symderive/ode/__init__.py
symderive/ode/numeric.py
symderive/ode/symbolic.py
symderive/optimize/__init__.py
symderive/optimize/core.py
symderive/patterns/__init__.py
symderive/patterns/functions.py
symderive/patterns/matching.py
symderive/plotting/__init__.py
symderive/plotting/core.py
symderive/probability/__init__.py
symderive/probability/distributions.py
symderive/regression/__init__.py
symderive-0.6.3.dist-info/METADATA
symderive-0.6.3.dist-info/WHEEL
symderive-0.6.3.dist-info/licenses/LICENSE
symderive-0.6.3.dist-info/RECORD
