Metadata-Version: 2.4
Name: symderive
Version: 0.6.3
Summary: A standalone symbolic engine for AI agents and mathematical computing
Project-URL: Homepage, https://github.com/closedform/deriver
Project-URL: Documentation, https://github.com/closedform/deriver#readme
Project-URL: Repository, https://github.com/closedform/deriver.git
Project-URL: Issues, https://github.com/closedform/deriver/issues
Author: Brandon DiNunno, Tom Mainiero, Victor (Mingsy) Chua
License-Expression: MIT
License-File: LICENSE
Keywords: ai-agents,algebra,calculus,cas,computer-algebra,differential-geometry,llm,mathematics,physics,symbolic,sympy
Classifier: Development Status :: 4 - Beta
Classifier: Intended Audience :: Developers
Classifier: Intended Audience :: Education
Classifier: Intended Audience :: Science/Research
Classifier: License :: OSI Approved :: MIT License
Classifier: Operating System :: OS Independent
Classifier: Programming Language :: Python :: 3
Classifier: Programming Language :: Python :: 3.12
Classifier: Topic :: Scientific/Engineering :: Mathematics
Classifier: Topic :: Scientific/Engineering :: Physics
Classifier: Topic :: Software Development :: Libraries :: Python Modules
Requires-Python: >=3.12
Requires-Dist: ipykernel>=7.1.0
Requires-Dist: matplotlib>=3.8
Requires-Dist: mpmath>=1.3
Requires-Dist: nbconvert>=7.16.6
Requires-Dist: numpy>=1.26
Requires-Dist: polars>=0.20
Requires-Dist: rich>=13.0
Requires-Dist: scipy>=1.12
Requires-Dist: sympy>=1.13
Provides-Extra: all
Requires-Dist: cvxpy>=1.4; extra == 'all'
Requires-Dist: marimo>=0.8; extra == 'all'
Requires-Dist: pysr>=0.19; extra == 'all'
Provides-Extra: dev
Requires-Dist: cvxpy>=1.4; extra == 'dev'
Requires-Dist: ipykernel>=6.29; extra == 'dev'
Requires-Dist: jupyter>=1.0; extra == 'dev'
Requires-Dist: marimo>=0.8; extra == 'dev'
Requires-Dist: nbformat>=5.10; extra == 'dev'
Requires-Dist: pytest-cov>=4.1; extra == 'dev'
Requires-Dist: pytest>=8.0; extra == 'dev'
Provides-Extra: notebooks
Requires-Dist: marimo>=0.8; extra == 'notebooks'
Provides-Extra: optimize
Requires-Dist: cvxpy>=1.4; extra == 'optimize'
Provides-Extra: regression
Requires-Dist: pysr>=0.19; extra == 'regression'
